calapy/__init__.py
calapy/array.py
calapy/check.py
calapy/clock.py
calapy/combinations.py
calapy/directory.py
calapy/download.py
calapy/format.py
calapy/hacks.py
calapy/image.py
calapy/lists.py
calapy/maths.py
calapy/mixamo.py
calapy/pkl.py
calapy/shutdown.py
calapy/strings.py
calapy/threading.py
calapy/txt.py
calapy/ml/__init__.py
calapy/ml/utilities.py
calapy/ml/rl/__init__.py
calapy/ml/rl/utilities.py
calapy/ml/rl/ql/__init__.py
calapy/ml/rl/ql/dqc/DQC_model.py
calapy/ml/rl/ql/dqc/DQC_model_methods.py
calapy/ml/rl/ql/dqc/__init__.py
calapy/ml/rl/ql/dqc/train_with_same_time_sizes.py
calapy/ml/rl/ql/dqn/__init__.py
calapy/ml/rl/ql/dqn/module.py
calapy/ml/rl/ql/dqn/module_old.py
calapy/ml/sl/__init__.py
calapy/ml/sl/dl/__init__.py
calapy/ml/sl/dl/devices.py
calapy/ml/sl/dl/preprocess.py
calapy/ml/sl/dl/tensors.py
calapy/ml/sl/dl/test.py
calapy/ml/sl/dl/train.py
calapy/ml/sl/dl/datasets/__init__.py
calapy/ml/sl/dl/datasets/csv_old.py
calapy/ml/sl/dl/datasets/image.py
calapy/ml/sl/dl/datasets/loaders.py
calapy/ml/sl/dl/datasets/loaders_old.py
calapy/ml/sl/dl/datasets/tools.py
calapy/ml/sl/dl/models/__init__.py
calapy/ml/sl/dl/models/a_way_to_edit_model_forward_method.py
calapy/ml/sl/dl/models/image.py
calapy/ml/sl/dl/models/model_tools.py
calapy/ml/sl/dl/models/multi_layers/__init__.py
calapy/ml/sl/dl/models/multi_layers/hetero.py
calapy/ml/sl/dl/models/multi_layers/homo/__init__.py
calapy/ml/sl/dl/models/multi_layers/homo/_base.py
calapy/ml/sl/dl/models/multi_layers/homo/fcns.py
calapy/ml/sl/dl/models/multi_layers/homo/rnns.py
calapy/ml/sl/dl/models/single_layers/__init__.py
calapy/ml/sl/dl/models/single_layers/non_trainable.py
calapy/ml/sl/dl/models/single_layers/trainable/__init__.py
calapy/ml/sl/dl/models/single_layers/trainable/conv.py
calapy/ml/sl/dl/models/single_layers/trainable/recurrent.py
calapy/ml/sl/dl/models/single_layers/trainable_with_non_trainable/__init__.py
calapy/ml/sl/dl/output_methods/__init__.py
calapy/ml/sl/dl/output_methods/general.py
calapy-0.2.0.4.dist-info/licenses/LICENSE.txt
calapy-0.2.0.4.dist-info/METADATA
calapy-0.2.0.4.dist-info/WHEEL
calapy-0.2.0.4.dist-info/top_level.txt
calapy-0.2.0.4.dist-info/RECORD
