Metadata-Version: 2.4
Name: calapy
Version: 0.2.0.4
Summary: Personal Package
Author-email: Carmelo Calafiore <dr.carmelo.calafiore@gmail.com>
Maintainer-email: Carmelo Calafiore <dr.carmelo.calafiore@gmail.com>
License-Expression: MIT
Project-URL: Repository, https://github.com/ccalafiore/CalaPy
Project-URL: Issues, https://github.com/ccalafiore/CalaPy/issues
Keywords: basic,tools,toolkit,toolbox,kit,utilities
Classifier: Programming Language :: Python :: 3
Classifier: Operating System :: OS Independent
Requires-Python: >=3.6
License-File: LICENSE.txt
Requires-Dist: numpy
Requires-Dist: scipy
Requires-Dist: pandas
Requires-Dist: opencv-contrib-python
Requires-Dist: matplotlib
Requires-Dist: selenium
Requires-Dist: pygame
Requires-Dist: torch
Requires-Dist: torchvision
Requires-Dist: Pillow
Dynamic: license-file
